Metadata-Version: 1.0
Name: ezmp
Version: 3.1.3.3.7
Summary: Multiprocessing done RIGHT.
Home-page: https://github.com/zardus/ezmp
Author: UNKNOWN
Author-email: UNKNOWN
License: UNKNOWN
Platform: UNKNOWN
